tmssh/__init__.py
tmssh/tmssh.py
tmssh-0.3.dist-info/licenses/LICENSE
tmssh-0.3.dist-info/METADATA
tmssh-0.3.dist-info/WHEEL
tmssh-0.3.dist-info/entry_points.txt
tmssh-0.3.dist-info/top_level.txt
tmssh-0.3.dist-info/RECORD
