Metadata-Version: 2.4
Name: tmssh
Version: 0.3
Summary: Simple SSH Manager
Author-email: Baguette Yeeter <baguetteyeeter@icloud.com>
License:                     GNU GENERAL PUBLIC LICENSE
Project-URL: Homepage, https://github.com/BaguetteYeeter/tmssh
Project-URL: Bug Tracker, https://github.com/BaguetteYeeter/tmssh/issues
Keywords: ssh,terminal,networking,openssh
Classifier: Programming Language :: Python :: 3
Classifier: Topic :: Utilities
Classifier: Topic :: Terminals
Classifier: Topic :: System :: Shells
Requires-Python: >=3.10
License-File: LICENSE
Dynamic: license-file
